klinecenter/__init__.py
klinecenter/k_api.py
klinecenter-0.1.4.dist-info/METADATA
klinecenter-0.1.4.dist-info/WHEEL
klinecenter-0.1.4.dist-info/top_level.txt
klinecenter-0.1.4.dist-info/RECORD
