Metadata-Version: 2.1
Name: klinecenter
Version: 0.1.4
License: Your license
Requires-Dist: pandas
Requires-Dist: requests
